seeq/addons/plot_curve/__init__.py
seeq/addons/plot_curve/__main__.py
seeq/addons/plot_curve/_add_on_main.py
seeq/addons/plot_curve/_copy.py
seeq/addons/plot_curve/_version.py
seeq/addons/plot_curve/backend/__init__.py
seeq/addons/plot_curve/backend/_backend.py
seeq/addons/plot_curve/backend/_equation.py
seeq/addons/plot_curve/deployment_notebook/PlotCurve.ipynb
seeq/addons/plot_curve/ui_components/__init__.py
seeq/addons/plot_curve/ui_components/_app_layout.py
seeq/addons/plot_curve/ui_components/_chart_component.py
seeq/addons/plot_curve/ui_components/_file_reader.py
seeq/addons/plot_curve/ui_components/_header.py
seeq/addons/plot_curve/ui_components/_tabbed_dataframe.py
seeq/addons/plot_curve/ui_components/templates/AppLayout.vue
seeq/addons/plot_curve/ui_components/templates/ChartComponent.vue
seeq/addons/plot_curve/ui_components/templates/FileReader.vue
seeq/addons/plot_curve/ui_components/templates/Header.vue
seeq/addons/plot_curve/ui_components/templates/TabbedDataFrame.vue
seeq/addons/plot_curve/utils/__init__.py
seeq/addons/plot_curve/utils/_decorators.py
seeq/addons/plot_curve/utils/_messaging.py
seeq_plot_curve-0.1.4.dist-info/LICENSE
seeq_plot_curve-0.1.4.dist-info/METADATA
seeq_plot_curve-0.1.4.dist-info/NOTICE
seeq_plot_curve-0.1.4.dist-info/WHEEL
seeq_plot_curve-0.1.4.dist-info/top_level.txt
seeq_plot_curve-0.1.4.dist-info/RECORD
