Metadata-Version: 2.1
Name: seeq-plot-curve
Version: 0.1.4
Summary: A Seeq add-on tool for fitting curves to tabular data and pushing resulting formulas to Seeq.
Home-page: https://github.com/seeq12/seeq-plot-curve
Author: Seeq Corporation
Author-email: applied.research@seeq.com
License: Apache License 2.0
Platform: UNKNOWN
Classifier: Programming Language :: Python :: 3.7
Classifier: License :: OSI Approved :: Apache Software License
Classifier: Operating System :: OS Independent
Requires-Python: >=3.7
License-File: LICENSE
License-File: NOTICE
Requires-Dist: ipywidgets >=7.6.3
Requires-Dist: ipyvuetify >=1.8.0
Requires-Dist: rx >=3.2.0
Requires-Dist: mpmath >=1.1.0
Requires-Dist: bqplot ==0.12.31
Requires-Dist: sympy >=1.9
Requires-Dist: traitlets >=5.1.0
Requires-Dist: numpy >=1.19.5
Requires-Dist: pandas !=1.3.0,>=1.2.3
Requires-Dist: IPython >=7.29.0
Requires-Dist: typeguard >=2.13.0
Requires-Dist: mixpanel >=4.9.0
Requires-Dist: pint >=0.17.0
